WhirlData/__init__.py
wday/__init__.py
wday-2.0.5.dist-info/METADATA
wday-2.0.5.dist-info/WHEEL
wday-2.0.5.dist-info/top_level.txt
wday-2.0.5.dist-info/RECORD
