Metadata-Version: 2.1
Name: wday
Version: 2.0.5
Summary: A simple Data storage language
Home-page: https://github.com/Whirlpool-Programmer/wday
Author: Whirlpool-Programmer
Author-email: whirlpool.programmer@outlook.com
License: MIT License
Platform: UNKNOWN
Classifier: Programming Language :: Python :: 3
Classifier: License :: OSI Approved :: MIT License
Classifier: Operating System :: OS Independent
